openfe/FeatureGenerator.py
openfe/FeatureSelector.py
openfe/__init__.py
openfe/openfe.py
openfe/utils.py
openfe-0.0.12.dist-info/LICENSE
openfe-0.0.12.dist-info/METADATA
openfe-0.0.12.dist-info/WHEEL
openfe-0.0.12.dist-info/top_level.txt
openfe-0.0.12.dist-info/RECORD
