Metadata-Version: 2.1
Name: openfe
Version: 0.0.12
Summary: OpenFE: automated feature generation with expert-level performance
Home-page: https://github.com/IIIS-Li-Group/OpenFE/
Author: Tianping Zhang
Author-email: ztp18@mails.tsinghua.edu.cn
Classifier: Programming Language :: Python :: 3
Classifier: License :: OSI Approved :: MIT License
Classifier: Operating System :: OS Independent
Requires-Python: >=3.6
License-File: LICENSE
Requires-Dist: numpy (>=1.19.3)
Requires-Dist: pandas (>=1.1.5)
Requires-Dist: scikit-learn (>=0.24.2)
Requires-Dist: lightgbm (>=3.3.2)
Requires-Dist: scipy (>=1.5.4)
Requires-Dist: tqdm
Requires-Dist: pyarrow
